teliqon_billing/__init__.py
teliqon_billing/billing.py
teliqon_billing/billing.pyi
teliqon_billing/core.py
teliqon_billing/exceptions.py
teliqon_billing/types.py
teliqon_billing-0.0.16.dist-info/LICENSE
teliqon_billing-0.0.16.dist-info/METADATA
teliqon_billing-0.0.16.dist-info/WHEEL
teliqon_billing-0.0.16.dist-info/top_level.txt
teliqon_billing-0.0.16.dist-info/RECORD
