Metadata-Version: 2.1
Name: teliqon-billing
Version: 0.0.16
Summary: Teliqon Billing API Python SDK
Author-email: Sidq <abba.dmytro@teliqon.io>
Project-URL: Admin, https://billing-api-dev.voiceflow.com.ua/admin/signup/
Project-URL: Company, https://teliqon.io/
Project-URL: Author, https://t.me/sidqdev
Classifier: Programming Language :: Python :: 3
Classifier: License :: OSI Approved :: MIT License
Classifier: Operating System :: OS Independent
Requires-Python: >=3.7
License-File: LICENSE
Requires-Dist: requests
